django_generic_tasks/__init__.py
django_generic_tasks/api.py
django_generic_tasks/apps.py
django_generic_tasks/backends.py
django_generic_tasks/migrations/__init__.py
django_generic_tasks/security.py
django_generic_tasks/task.py
django_generic_tasks/urls.py
django_generic_tasks/utils.py
django_generic_tasks-0.5.1.dist-info/WHEEL
django_generic_tasks-0.5.1.dist-info/METADATA
django_generic_tasks-0.5.1.dist-info/RECORD
