Metadata-Version: 2.1
Name: django-generic-tasks
Version: 0.5.1
Summary: Active Job for Django
Home-page: https://github.com/yi-jiayu/django-generic-tasks
Author: Jiayu Yi
Author-email: yijiayu@gmail.com
Requires-Python: >=3.9,<4.0
Classifier: Programming Language :: Python :: 3
Classifier: Programming Language :: Python :: 3.10
Classifier: Programming Language :: Python :: 3.9
Requires-Dist: CacheControl (>=0.12.11,<0.13.0)
Requires-Dist: Django (>=4.0.4,<5.0.0)
Requires-Dist: django-ninja (>=0.18.0,<0.19.0)
Requires-Dist: google-auth (>=2.6.6,<3.0.0)
Requires-Dist: google-cloud-tasks (>=2.8.1,<3.0.0)
Requires-Dist: pydantic (>=1.9.0,<2.0.0)
Requires-Dist: requests (>=2.27.1,<3.0.0)
